knifes/__init__.py
knifes/aes.py
knifes/aes_.py
knifes/digests.py
knifes/exception_handlers.py
knifes/logging.py
knifes/media.py
knifes/network.py
knifes/operators.py
knifes/package.py
knifes/shell.py
knifes/strings.py
knifes/times.py
knifes/urls.py
knifes/useragent.py
knifes/deploy/__init__.py
knifes/deploy/celery.py
knifes/deploy/main.py
fast_knifes-0.0.47.dist-info/METADATA
fast_knifes-0.0.47.dist-info/WHEEL
fast_knifes-0.0.47.dist-info/entry_points.txt
fast_knifes-0.0.47.dist-info/top_level.txt
fast_knifes-0.0.47.dist-info/RECORD
