Metadata-Version: 2.1
Name: fast-knifes
Version: 0.0.47
Summary: Fast Swiss Army Knife
Home-page: https://github.com/
Author: knifes
Author-email: author@example.com
Classifier: Programming Language :: Python :: 3
Classifier: License :: OSI Approved :: MIT License
Classifier: Operating System :: OS Independent
Requires-Python: >=3.10
Requires-Dist: anyio
Requires-Dist: typer
Requires-Dist: python-dotenv
Requires-Dist: concurrent-log-handler
